setup.py
srsh_distributions/Binomialdistribution.py
srsh_distributions/Gaussiandistribution.py
srsh_distributions/Generaldistribution.py
srsh_distributions/__init__.py
srsh_distributions.egg-info/PKG-INFO
srsh_distributions.egg-info/SOURCES.txt
srsh_distributions.egg-info/dependency_links.txt
srsh_distributions.egg-info/not-zip-safe
srsh_distributions.egg-info/top_level.txt