Metadata-Version: 1.0
Name: srsh-distributions
Version: 1.0
Summary: Gaussian distribution and Binomial distribution
Home-page: UNKNOWN
Author: Srinivas Shekar
Author-email: srinivasshekar10@gmail.com
License: UNKNOWN
Platform: UNKNOWN
